richuru.py
richuru-0.1.1.dist-info/WHEEL
richuru-0.1.1.dist-info/METADATA
richuru-0.1.1.dist-info/license_files/LICENSE
richuru-0.1.1.dist-info/RECORD
