Metadata-Version: 2.1
Name: richuru
Version: 0.1.1
Summary: a bridge between loguru & rich, rich's powerful render in loguru!
License: MIT
Author-email: GreyElaina <GreyElaina@outlook.com>
Requires-Python: >=3.8
Requires-Dist: loguru>=0.6.0
Requires-Dist: rich>=12.4.4
